README.md
setup.py
heartfixer/__init__.py
heartfixer.egg-info/PKG-INFO
heartfixer.egg-info/SOURCES.txt
heartfixer.egg-info/dependency_links.txt
heartfixer.egg-info/requires.txt
heartfixer.egg-info/top_level.txt