Metadata-Version: 2.1
Name: heartfixer
Version: 0.0.1
Summary: Fix things using AI / Python library
Home-page: https://github.com/smallcloudai/heartfixer
Author: Small Magellanic Cloud AI Ltd.
Author-email: cli-tool@smallcloud.tech
License: GNU GPLv3
Classifier: Development Status :: 3 - Alpha
Classifier: Topic :: Scientific/Engineering :: Artificial Intelligence
Classifier: Intended Audience :: Developers
Classifier: License :: OSI Approved :: GNU General Public License v3 (GPLv3)
Classifier: Environment :: Console
Classifier: Operating System :: OS Independent
